m3u8tool/__init__.py
m3u8tool/__version__.py
m3u8tool/app.py
m3u8tool/concatenator.py
m3u8tool/converter.py
m3u8tool/io.py
m3u8tool/splitter.py
m3u8tool-0.1.1.dist-info/LICENSE
m3u8tool-0.1.1.dist-info/METADATA
m3u8tool-0.1.1.dist-info/WHEEL
m3u8tool-0.1.1.dist-info/entry_points.txt
m3u8tool-0.1.1.dist-info/top_level.txt
m3u8tool-0.1.1.dist-info/RECORD
