Metadata-Version: 2.1
Name: m3u8tool
Version: 0.1.1
Summary: A HTTP Live Streaming (HLS) manipulation tool
Home-page: https://github.com/kurusugawa-computer/m3u8tool
Author: squld
Author-email: sato@kurusugawa.jp
License: Apache License 2.0
Keywords: m3u8
Platform: UNKNOWN
Classifier: Development Status :: 4 - Beta
Classifier: Intended Audience :: Developers
Classifier: License :: OSI Approved :: Apache Software License
Classifier: Programming Language :: Python
Classifier: Programming Language :: Python :: 3 :: Only
Classifier: Programming Language :: Python :: 3.5
Classifier: Programming Language :: Python :: 3.6
Classifier: Programming Language :: Python :: 3.7
Classifier: Topic :: Utilities
Classifier: Operating System :: OS Independent
Requires-Python: >=3.5
